{
  "table_name": "Honor_war_buildingTable",
  "row_count": 91,
  "data": [
    {"Id": 1, "Season": 0, "Name": 912085, "GroupName": 912101, "Group": 3, "BuildingSize": 8, "Prefab": "World_EarlyBattle_MineBig", "LodPic": "ResCitrine4", "LodPicScale": 0, "LodIcon": "lod_GW_City_dakuang", "Icon": "lod_GW_City_dakuang", "PosArray": [50, 1150], "PosArrayLength": 2, "FirstOccupyTime": 30, "OccupyTime": 10, "FirstOccupy": 9000, "Occupy": 6000, "FirstPersonalOccupy": 4500, "PersonalOccupy": 3000, "RuleShow": 1, "Describe": 912086, "BuffArray": null, "BuffArrayLength": 0, "BuffDic": {}, "WorldcityId": 0, "Index": 0},
    {"Id": 2, "Season": 0, "Name": 912087, "GroupName": 912099, "Group": 1, "BuildingSize": 2, "Prefab": "World_EarlyBattle_MineMid", "LodPic": "ResCitrine2", "LodPicScale": 0, "LodIcon": "lod_GW_City_zhongkuang", "Icon": "lod_GW_City_zhongkuang", "PosArray": [63, 1118], "PosArrayLength": 2, "FirstOccupyTime": 15, "OccupyTime": 5, "FirstOccupy": 4500, "Occupy": 2250, "FirstPersonalOccupy": 3000, "PersonalOccupy": 1500, "RuleShow": 1, "Describe": 912089, "BuffArray": null, "BuffArrayLength": 0, "BuffDic": {}, "WorldcityId": 0, "Index": 1},
    {"Id": 3, "Season": 0, "Name": 912088, "GroupName": 912099, "Group": 1, "BuildingSize": 2, "Prefab": "World_EarlyBattle_MineMid", "LodPic": "ResCitrine2", "LodPicScale": 0, "LodIcon": "lod_GW_City_zhongkuang", "Icon": "lod_GW_City_zhongkuang", "PosArray": [37, 1182], "PosArrayLength": 2, "FirstOccupyTime": 15, "OccupyTime": 5, "FirstOccupy": 4500, "Occupy": 2250, "FirstPersonalOccupy": 3000, "PersonalOccupy": 1500, "RuleShow": 1, "Describe": 912089, "BuffArray": null, "BuffArrayLength": 0, "BuffDic": {}, "WorldcityId": 0, "Index": 2},
    {"Id": 4, "Season": 0, "Name": 912090, "GroupName": 912099, "Group": 1, "BuildingSize": 1, "Prefab": "World_EarlyBattle_MineSmall", "LodPic": "ResCitrine1", "LodPicScale": 0, "LodIcon": "lod_GW_City_xiaokuang", "Icon": "lod_GW_City_xiaokuang", "PosArray": [82, 1137], "PosArrayLength": 2, "FirstOccupyTime": 15, "OccupyTime": 5, "FirstOccupy": 3000, "Occupy": 1500, "FirstPersonalOccupy": 2000, "PersonalOccupy": 1000, "RuleShow": 1, "Describe": 912092, "BuffArray": null, "BuffArrayLength": 0, "BuffDic": {}, "WorldcityId": 0, "Index": 3},
    {"Id": 5, "Season": 0, "Name": 912091, "GroupName": 912099, "Group": 1, "BuildingSize": 1, "Prefab": "World_EarlyBattle_MineSmall", "LodPic": "ResCitrine1", "LodPicScale": 0, "LodIcon": "lod_GW_City_xiaokuang", "Icon": "lod_GW_City_xiaokuang", "PosArray": [18, 1163], "PosArrayLength": 2, "FirstOccupyTime": 15, "OccupyTime": 5, "FirstOccupy": 3000, "Occupy": 1500, "FirstPersonalOccupy": 2000, "PersonalOccupy": 1000, "RuleShow": 1, "Describe": 912092, "BuffArray": null, "BuffArrayLength": 0, "BuffDic": {}, "WorldcityId": 0, "Index": 4},
    {"Id": 6, "Season": 0, "Name": 912093, "GroupName": 912099, "Group": 1, "BuildingSize": 2, "Prefab": "World_EarlyBattle_Radar", "LodPic": "img_earlyBattle_leida", "LodPicScale": 0, "LodIcon": "icon_chiji_leida_01", "Icon": "lod_GW_City_leida", "PosArray": [15, 1115], "PosArrayLength": 2, "FirstOccupyTime": 15, "OccupyTime": 5, "FirstOccupy": 900, "Occupy": 450, "FirstPersonalOccupy": 600, "PersonalOccupy": 300, "RuleShow": 1, "Describe": 912095, "BuffArray": ["10825;60", "60;50"], "BuffArrayLength": 2, "BuffDic": {"10825": 60, "60": 50}, "WorldcityId": 0, "Index": 5},
    {"Id": 7, "Season": 0, "Name": 912094, "GroupName": 912099, "Group": 1, "BuildingSize": 2, "Prefab": "World_EarlyBattle_Radar", "LodPic": "img_earlyBattle_leida", "LodPicScale": 0, "LodIcon": "icon_chiji_leida_01", "Icon": "lod_GW_City_leida", "PosArray": [85, 1185], "PosArrayLength": 2, "FirstOccupyTime": 15, "OccupyTime": 5, "FirstOccupy": 900, "Occupy": 450, "FirstPersonalOccupy": 600, "PersonalOccupy": 300, "RuleShow": 1, "Describe": 912095, "BuffArray": ["10825;60", "60;50"], "BuffArrayLength": 2, "BuffDic": {"10825": 60, "60": 50}, "WorldcityId": 0, "Index": 6},
    {"Id": 8, "Season": 0, "Name": 912096, "GroupName": 912100, "Group": 2, "BuildingSize": 2, "Prefab": "World_EarlyBattle_Combat", "LodPic": "img_earlyBattle_junhuo", "LodPicScale": 0, "LodIcon": "icon_chiji_junhuoku_01", "Icon": "lod_GW_City_zhanbei", "PosArray": [38, 1138], "PosArrayLength": 2, "FirstOccupyTime": 15, "OccupyTime": 5, "FirstOccupy": 900, "Occupy": 450, "FirstPersonalOccupy": 600, "PersonalOccupy": 300, "RuleShow": 1, "Describe": 912097, "BuffArray": ["20081;20"], "BuffArrayLength": 1, "BuffDic": {"20081": 20}, "WorldcityId": 0, "Index": 7},
    {"Id": 9, "Season": 0, "Name": 912218, "GroupName": 912100, "Group": 2, "BuildingSize": 2, "Prefab": "World_EarlyBattle_Defense", "LodPic": "img_earlyBattle_cheku", "LodPicScale": 0, "LodIcon": "icon_chiji_cheku_01", "Icon": "lod_GW_City_fangbei", "PosArray": [62, 1162], "PosArrayLength": 2, "FirstOccupyTime": 15, "OccupyTime": 5, "FirstOccupy": 900, "Occupy": 450, "FirstPersonalOccupy": 600, "PersonalOccupy": 300, "RuleShow": 1, "Describe": 912219, "BuffArray": ["20082;20"], "BuffArrayLength": 1, "BuffDic": {"20082": 20}, "WorldcityId": 0, "Index": 8},
    {"Id": 10, "Season": 0, "Name": 912220, "GroupName": 912099, "Group": 1, "BuildingSize": 2, "Prefab": "World_EarlyBattle_Hospital", "LodPic": "img_earlyBattle_yiyuan", "LodPicScale": 0, "LodIcon": "icon_chiji_yiyuan_01", "Icon": "lod_GW_City_yiyuan", "PosArray": [40, 1115], "PosArrayLength": 2, "FirstOccupyTime": 15, "OccupyTime": 5, "FirstOccupy": 900, "Occupy": 450, "FirstPersonalOccupy": 600, "PersonalOccupy": 300, "RuleShow": 1, "Describe": 912224, "BuffArray": ["20065;120"], "BuffArrayLength": 1, "BuffDic": {"20065": 120}, "WorldcityId": 0, "Index": 9},
    {"Id": 11, "Season": 0, "Name": 912221, "GroupName": 912099, "Group": 1, "BuildingSize": 2, "Prefab": "World_EarlyBattle_Hospital", "LodPic": "img_earlyBattle_yiyuan", "LodPicScale": 0, "LodIcon": "icon_chiji_yiyuan_01", "Icon": "lod_GW_City_yiyuan", "PosArray": [15, 1140], "PosArrayLength": 2, "FirstOccupyTime": 15, "OccupyTime": 5, "FirstOccupy": 900, "Occupy": 450, "FirstPersonalOccupy": 600, "PersonalOccupy": 300, "RuleShow": 1, "Describe": 912224, "BuffArray": ["20065;120"], "BuffArrayLength": 1, "BuffDic": {"20065": 120}, "WorldcityId": 0, "Index": 10},
    {"Id": 12, "Season": 0, "Name": 912222, "GroupName": 912099, "Group": 1, "BuildingSize": 2, "Prefab": "World_EarlyBattle_Hospital", "LodPic": "img_earlyBattle_yiyuan", "LodPicScale": 0, "LodIcon": "icon_chiji_yiyuan_01", "Icon": "lod_GW_City_yiyuan", "PosArray": [85, 1160], "PosArrayLength": 2, "FirstOccupyTime": 15, "OccupyTime": 5, "FirstOccupy": 900, "Occupy": 450, "FirstPersonalOccupy": 600, "PersonalOccupy": 300, "RuleShow": 1, "Describe": 912224, "BuffArray": ["20065;120"], "BuffArrayLength": 1, "BuffDic": {"20065": 120}, "WorldcityId": 0, "Index": 11},
    {"Id": 13, "Season": 0, "Name": 912223, "GroupName": 912099, "Group": 1, "BuildingSize": 2, "Prefab": "World_EarlyBattle_Hospital", "LodPic": "img_earlyBattle_yiyuan", "LodPicScale": 0, "LodIcon": "icon_chiji_yiyuan_01", "Icon": "lod_GW_City_yiyuan", "PosArray": [60, 1185], "PosArrayLength": 2, "FirstOccupyTime": 15, "OccupyTime": 5, "FirstOccupy": 900, "Occupy": 450, "FirstPersonalOccupy": 600, "PersonalOccupy": 300, "RuleShow": 1, "Describe": 912224, "BuffArray": ["20065;120"], "BuffArrayLength": 1, "BuffDic": {"20065": 120}, "WorldcityId": 0, "Index": 12},
    {"Id": 14, "Season": 1, "Name": 912085, "GroupName": 912101, "Group": 3, "BuildingSize": 8, "Prefab": "World_EarlyBattle_MineBig", "LodPic": "ResCitrine4", "LodPicScale": 0, "LodIcon": "lod_GW_City_dakuang", "Icon": "lod_GW_City_dakuang", "PosArray": [50, 1150], "PosArrayLength": 2, "FirstOccupyTime": 30, "OccupyTime": 10, "FirstOccupy": 9000, "Occupy": 6000, "FirstPersonalOccupy": 4500, "PersonalOccupy": 3000, "RuleShow": 1, "Describe": 912086, "BuffArray": null, "BuffArrayLength": 0, "BuffDic": {}, "WorldcityId": 0, "Index": 13},
    {"Id": 15, "Season": 1, "Name": 912087, "GroupName": 912099, "Group": 1, "BuildingSize": 2, "Prefab": "World_EarlyBattle_MineMid", "LodPic": "ResCitrine2", "LodPicScale": 0, "LodIcon": "lod_GW_City_zhongkuang", "Icon": "lod_GW_City_zhongkuang", "PosArray": [63, 1118], "PosArrayLength": 2, "FirstOccupyTime": 15, "OccupyTime": 5, "FirstOccupy": 4500, "Occupy": 2250, "FirstPersonalOccupy": 3000, "PersonalOccupy": 1500, "RuleShow": 1, "Describe": 912089, "BuffArray": null, "BuffArrayLength": 0, "BuffDic": {}, "WorldcityId": 0, "Index": 14},
    {"Id": 16, "Season": 1, "Name": 912088, "GroupName": 912099, "Group": 1, "BuildingSize": 2, "Prefab": "World_EarlyBattle_MineMid", "LodPic": "ResCitrine2", "LodPicScale": 0, "LodIcon": "lod_GW_City_zhongkuang", "Icon": "lod_GW_City_zhongkuang", "PosArray": [37, 1182], "PosArrayLength": 2, "FirstOccupyTime": 15, "OccupyTime": 5, "FirstOccupy": 4500, "Occupy": 2250, "FirstPersonalOccupy": 3000, "PersonalOccupy": 1500, "RuleShow": 1, "Describe": 912089, "BuffArray": null, "BuffArrayLength": 0, "BuffDic": {}, "WorldcityId": 0, "Index": 15},
    {"Id": 17, "Season": 1, "Name": 912090, "GroupName": 912099, "Group": 1, "BuildingSize": 1, "Prefab": "World_EarlyBattle_MineSmall", "LodPic": "ResCitrine1", "LodPicScale": 0, "LodIcon": "lod_GW_City_xiaokuang", "Icon": "lod_GW_City_xiaokuang", "PosArray": [82, 1137], "PosArrayLength": 2, "FirstOccupyTime": 15, "OccupyTime": 5, "FirstOccupy": 3000, "Occupy": 1500, "FirstPersonalOccupy": 2000, "PersonalOccupy": 1000, "RuleShow": 1, "Describe": 912092, "BuffArray": null, "BuffArrayLength": 0, "BuffDic": {}, "WorldcityId": 0, "Index": 16},
    {"Id": 18, "Season": 1, "Name": 912091, "GroupName": 912099, "Group": 1, "BuildingSize": 1, "Prefab": "World_EarlyBattle_MineSmall", "LodPic": "ResCitrine1", "LodPicScale": 0, "LodIcon": "lod_GW_City_xiaokuang", "Icon": "lod_GW_City_xiaokuang", "PosArray": [18, 1163], "PosArrayLength": 2, "FirstOccupyTime": 15, "OccupyTime": 5, "FirstOccupy": 3000, "Occupy": 1500, "FirstPersonalOccupy": 2000, "PersonalOccupy": 1000, "RuleShow": 1, "Describe": 912092, "BuffArray": null, "BuffArrayLength": 0, "BuffDic": {}, "WorldcityId": 0, "Index": 17},
    {"Id": 19, "Season": 1, "Name": 912093, "GroupName": 912099, "Group": 1, "BuildingSize": 2, "Prefab": "World_EarlyBattle_Radar", "LodPic": "img_earlyBattle_leida", "LodPicScale": 0, "LodIcon": "icon_chiji_leida_01", "Icon": "lod_GW_City_leida", "PosArray": [15, 1115], "PosArrayLength": 2, "FirstOccupyTime": 15, "OccupyTime": 5, "FirstOccupy": 900, "Occupy": 450, "FirstPersonalOccupy": 600, "PersonalOccupy": 300, "RuleShow": 1, "Describe": 912095, "BuffArray": ["10825;60", "60;50"], "BuffArrayLength": 2, "BuffDic": {"10825": 60, "60": 50}, "WorldcityId": 0, "Index": 18},
    {"Id": 20, "Season": 1, "Name": 912094, "GroupName": 912099, "Group": 1, "BuildingSize": 2, "Prefab": "World_EarlyBattle_Radar", "LodPic": "img_earlyBattle_leida", "LodPicScale": 0, "LodIcon": "icon_chiji_leida_01", "Icon": "lod_GW_City_leida", "PosArray": [85, 1185], "PosArrayLength": 2, "FirstOccupyTime": 15, "OccupyTime": 5, "FirstOccupy": 900, "Occupy": 450, "FirstPersonalOccupy": 600, "PersonalOccupy": 300, "RuleShow": 1, "Describe": 912095, "BuffArray": ["10825;60", "60;50"], "BuffArrayLength": 2, "BuffDic": {"10825": 60, "60": 50}, "WorldcityId": 0, "Index": 19},
    {"Id": 21, "Season": 1, "Name": 912096, "GroupName": 912100, "Group": 2, "BuildingSize": 2, "Prefab": "World_EarlyBattle_Combat", "LodPic": "img_earlyBattle_junhuo", "LodPicScale": 0, "LodIcon": "icon_chiji_junhuoku_01", "Icon": "lod_GW_City_zhanbei", "PosArray": [38, 1138], "PosArrayLength": 2, "FirstOccupyTime": 15, "OccupyTime": 5, "FirstOccupy": 900, "Occupy": 450, "FirstPersonalOccupy": 600, "PersonalOccupy": 300, "RuleShow": 1, "Describe": 912097, "BuffArray": ["20081;20"], "BuffArrayLength": 1, "BuffDic": {"20081": 20}, "WorldcityId": 0, "Index": 20},
    {"Id": 22, "Season": 1, "Name": 912218, "GroupName": 912100, "Group": 2, "BuildingSize": 2, "Prefab": "World_EarlyBattle_Defense", "LodPic": "img_earlyBattle_cheku", "LodPicScale": 0, "LodIcon": "icon_chiji_cheku_01", "Icon": "lod_GW_City_fangbei", "PosArray": [62, 1162], "PosArrayLength": 2, "FirstOccupyTime": 15, "OccupyTime": 5, "FirstOccupy": 900, "Occupy": 450, "FirstPersonalOccupy": 600, "PersonalOccupy": 300, "RuleShow": 1, "Describe": 912219, "BuffArray": ["20082;20"], "BuffArrayLength": 1, "BuffDic": {"20082": 20}, "WorldcityId": 0, "Index": 21},
    {"Id": 23, "Season": 1, "Name": 912220, "GroupName": 912099, "Group": 1, "BuildingSize": 2, "Prefab": "World_EarlyBattle_Hospital", "LodPic": "img_earlyBattle_yiyuan", "LodPicScale": 0, "LodIcon": "icon_chiji_yiyuan_01", "Icon": "lod_GW_City_yiyuan", "PosArray": [40, 1115], "PosArrayLength": 2, "FirstOccupyTime": 15, "OccupyTime": 5, "FirstOccupy": 900, "Occupy": 450, "FirstPersonalOccupy": 600, "PersonalOccupy": 300, "RuleShow": 1, "Describe": 912224, "BuffArray": ["20065;120"], "BuffArrayLength": 1, "BuffDic": {"20065": 120}, "WorldcityId": 0, "Index": 22},
    {"Id": 24, "Season": 1, "Name": 912221, "GroupName": 912099, "Group": 1, "BuildingSize": 2, "Prefab": "World_EarlyBattle_Hospital", "LodPic": "img_earlyBattle_yiyuan", "LodPicScale": 0, "LodIcon": "icon_chiji_yiyuan_01", "Icon": "lod_GW_City_yiyuan", "PosArray": [15, 1140], "PosArrayLength": 2, "FirstOccupyTime": 15, "OccupyTime": 5, "FirstOccupy": 900, "Occupy": 450, "FirstPersonalOccupy": 600, "PersonalOccupy": 300, "RuleShow": 1, "Describe": 912224, "BuffArray": ["20065;120"], "BuffArrayLength": 1, "BuffDic": {"20065": 120}, "WorldcityId": 0, "Index": 23},
    {"Id": 25, "Season": 1, "Name": 912222, "GroupName": 912099, "Group": 1, "BuildingSize": 2, "Prefab": "World_EarlyBattle_Hospital", "LodPic": "img_earlyBattle_yiyuan", "LodPicScale": 0, "LodIcon": "icon_chiji_yiyuan_01", "Icon": "lod_GW_City_yiyuan", "PosArray": [85, 1160], "PosArrayLength": 2, "FirstOccupyTime": 15, "OccupyTime": 5, "FirstOccupy": 900, "Occupy": 450, "FirstPersonalOccupy": 600, "PersonalOccupy": 300, "RuleShow": 1, "Describe": 912224, "BuffArray": ["20065;120"], "BuffArrayLength": 1, "BuffDic": {"20065": 120}, "WorldcityId": 0, "Index": 24},
    {"Id": 26, "Season": 1, "Name": 912223, "GroupName": 912099, "Group": 1, "BuildingSize": 2, "Prefab": "World_EarlyBattle_Hospital", "LodPic": "img_earlyBattle_yiyuan", "LodPicScale": 0, "LodIcon": "icon_chiji_yiyuan_01", "Icon": "lod_GW_City_yiyuan", "PosArray": [60, 1185], "PosArrayLength": 2, "FirstOccupyTime": 15, "OccupyTime": 5, "FirstOccupy": 900, "Occupy": 450, "FirstPersonalOccupy": 600, "PersonalOccupy": 300, "RuleShow": 1, "Describe": 912224, "BuffArray": ["20065;120"], "BuffArrayLength": 1, "BuffDic": {"20065": 120}, "WorldcityId": 0, "Index": 25},
    {"Id": 27, "Season": 2, "Name": 912085, "GroupName": 912101, "Group": 3, "BuildingSize": 8, "Prefab": "World_EarlyBattle_MineBig", "LodPic": "ResCitrine4", "LodPicScale": 0, "LodIcon": "lod_GW_City_dakuang", "Icon": "lod_GW_City_dakuang", "PosArray": [50, 1150], "PosArrayLength": 2, "FirstOccupyTime": 30, "OccupyTime": 10, "FirstOccupy": 9000, "Occupy": 6000, "FirstPersonalOccupy": 4500, "PersonalOccupy": 3000, "RuleShow": 1, "Describe": 912086, "BuffArray": null, "BuffArrayLength": 0, "BuffDic": {}, "WorldcityId": 0, "Index": 26},
    {"Id": 28, "Season": 2, "Name": 912087, "GroupName": 912099, "Group": 1, "BuildingSize": 2, "Prefab": "World_EarlyBattle_MineMid", "LodPic": "ResCitrine2", "LodPicScale": 0, "LodIcon": "lod_GW_City_zhongkuang", "Icon": "lod_GW_City_zhongkuang", "PosArray": [63, 1118], "PosArrayLength": 2, "FirstOccupyTime": 15, "OccupyTime": 5, "FirstOccupy": 4500, "Occupy": 2250, "FirstPersonalOccupy": 3000, "PersonalOccupy": 1500, "RuleShow": 1, "Describe": 912089, "BuffArray": null, "BuffArrayLength": 0, "BuffDic": {}, "WorldcityId": 0, "Index": 27},
    {"Id": 29, "Season": 2, "Name": 912088, "GroupName": 912099, "Group": 1, "BuildingSize": 2, "Prefab": "World_EarlyBattle_MineMid", "LodPic": "ResCitrine2", "LodPicScale": 0, "LodIcon": "lod_GW_City_zhongkuang", "Icon": "lod_GW_City_zhongkuang", "PosArray": [37, 1182], "PosArrayLength": 2, "FirstOccupyTime": 15, "OccupyTime": 5, "FirstOccupy": 4500, "Occupy": 2250, "FirstPersonalOccupy": 3000, "PersonalOccupy": 1500, "RuleShow": 1, "Describe": 912089, "BuffArray": null, "BuffArrayLength": 0, "BuffDic": {}, "WorldcityId": 0, "Index": 28},
    {"Id": 30, "Season": 2, "Name": 912090, "GroupName": 912099, "Group": 1, "BuildingSize": 1, "Prefab": "World_EarlyBattle_MineSmall", "LodPic": "ResCitrine1", "LodPicScale": 0, "LodIcon": "lod_GW_City_xiaokuang", "Icon": "lod_GW_City_xiaokuang", "PosArray": [82, 1137], "PosArrayLength": 2, "FirstOccupyTime": 15, "OccupyTime": 5, "FirstOccupy": 3000, "Occupy": 1500, "FirstPersonalOccupy": 2000, "PersonalOccupy": 1000, "RuleShow": 1, "Describe": 912092, "BuffArray": null, "BuffArrayLength": 0, "BuffDic": {}, "WorldcityId": 0, "Index": 29},
    {"Id": 31, "Season": 2, "Name": 912091, "GroupName": 912099, "Group": 1, "BuildingSize": 1, "Prefab": "World_EarlyBattle_MineSmall", "LodPic": "ResCitrine1", "LodPicScale": 0, "LodIcon": "lod_GW_City_xiaokuang", "Icon": "lod_GW_City_xiaokuang", "PosArray": [18, 1163], "PosArrayLength": 2, "FirstOccupyTime": 15, "OccupyTime": 5, "FirstOccupy": 3000, "Occupy": 1500, "FirstPersonalOccupy": 2000, "PersonalOccupy": 1000, "RuleShow": 1, "Describe": 912092, "BuffArray": null, "BuffArrayLength": 0, "BuffDic": {}, "WorldcityId": 0, "Index": 30},
    {"Id": 32, "Season": 2, "Name": 912093, "GroupName": 912099, "Group": 1, "BuildingSize": 2, "Prefab": "World_EarlyBattle_Radar", "LodPic": "img_earlyBattle_leida", "LodPicScale": 0, "LodIcon": "icon_chiji_leida_01", "Icon": "lod_GW_City_leida", "PosArray": [15, 1115], "PosArrayLength": 2, "FirstOccupyTime": 15, "OccupyTime": 5, "FirstOccupy": 900, "Occupy": 450, "FirstPersonalOccupy": 600, "PersonalOccupy": 300, "RuleShow": 1, "Describe": 912095, "BuffArray": ["10825;60", "60;50"], "BuffArrayLength": 2, "BuffDic": {"10825": 60, "60": 50}, "WorldcityId": 0, "Index": 31},
    {"Id": 33, "Season": 2, "Name": 912094, "GroupName": 912099, "Group": 1, "BuildingSize": 2, "Prefab": "World_EarlyBattle_Radar", "LodPic": "img_earlyBattle_leida", "LodPicScale": 0, "LodIcon": "icon_chiji_leida_01", "Icon": "lod_GW_City_leida", "PosArray": [85, 1185], "PosArrayLength": 2, "FirstOccupyTime": 15, "OccupyTime": 5, "FirstOccupy": 900, "Occupy": 450, "FirstPersonalOccupy": 600, "PersonalOccupy": 300, "RuleShow": 1, "Describe": 912095, "BuffArray": ["10825;60", "60;50"], "BuffArrayLength": 2, "BuffDic": {"10825": 60, "60": 50}, "WorldcityId": 0, "Index": 32},
    {"Id": 34, "Season": 2, "Name": 912096, "GroupName": 912100, "Group": 2, "BuildingSize": 2, "Prefab": "World_EarlyBattle_Combat", "LodPic": "img_earlyBattle_junhuo", "LodPicScale": 0, "LodIcon": "icon_chiji_junhuoku_01", "Icon": "lod_GW_City_zhanbei", "PosArray": [38, 1138], "PosArrayLength": 2, "FirstOccupyTime": 15, "OccupyTime": 5, "FirstOccupy": 900, "Occupy": 450, "FirstPersonalOccupy": 600, "PersonalOccupy": 300, "RuleShow": 1, "Describe": 912097, "BuffArray": ["20081;20"], "BuffArrayLength": 1, "BuffDic": {"20081": 20}, "WorldcityId": 0, "Index": 33},
    {"Id": 35, "Season": 2, "Name": 912218, "GroupName": 912100, "Group": 2, "BuildingSize": 2, "Prefab": "World_EarlyBattle_Defense", "LodPic": "img_earlyBattle_cheku", "LodPicScale": 0, "LodIcon": "icon_chiji_cheku_01", "Icon": "lod_GW_City_fangbei", "PosArray": [62, 1162], "PosArrayLength": 2, "FirstOccupyTime": 15, "OccupyTime": 5, "FirstOccupy": 900, "Occupy": 450, "FirstPersonalOccupy": 600, "PersonalOccupy": 300, "RuleShow": 1, "Describe": 912219, "BuffArray": ["20082;20"], "BuffArrayLength": 1, "BuffDic": {"20082": 20}, "WorldcityId": 0, "Index": 34},
    {"Id": 36, "Season": 2, "Name": 912220, "GroupName": 912099, "Group": 1, "BuildingSize": 2, "Prefab": "World_EarlyBattle_Hospital", "LodPic": "img_earlyBattle_yiyuan", "LodPicScale": 0, "LodIcon": "icon_chiji_yiyuan_01", "Icon": "lod_GW_City_yiyuan", "PosArray": [40, 1115], "PosArrayLength": 2, "FirstOccupyTime": 15, "OccupyTime": 5, "FirstOccupy": 900, "Occupy": 450, "FirstPersonalOccupy": 600, "PersonalOccupy": 300, "RuleShow": 1, "Describe": 912224, "BuffArray": ["20065;120"], "BuffArrayLength": 1, "BuffDic": {"20065": 120}, "WorldcityId": 0, "Index": 35},
    {"Id": 37, "Season": 2, "Name": 912221, "GroupName": 912099, "Group": 1, "BuildingSize": 2, "Prefab": "World_EarlyBattle_Hospital", "LodPic": "img_earlyBattle_yiyuan", "LodPicScale": 0, "LodIcon": "icon_chiji_yiyuan_01", "Icon": "lod_GW_City_yiyuan", "PosArray": [15, 1140], "PosArrayLength": 2, "FirstOccupyTime": 15, "OccupyTime": 5, "FirstOccupy": 900, "Occupy": 450, "FirstPersonalOccupy": 600, "PersonalOccupy": 300, "RuleShow": 1, "Describe": 912224, "BuffArray": ["20065;120"], "BuffArrayLength": 1, "BuffDic": {"20065": 120}, "WorldcityId": 0, "Index": 36},
    {"Id": 38, "Season": 2, "Name": 912222, "GroupName": 912099, "Group": 1, "BuildingSize": 2, "Prefab": "World_EarlyBattle_Hospital", "LodPic": "img_earlyBattle_yiyuan", "LodPicScale": 0, "LodIcon": "icon_chiji_yiyuan_01", "Icon": "lod_GW_City_yiyuan", "PosArray": [85, 1160], "PosArrayLength": 2, "FirstOccupyTime": 15, "OccupyTime": 5, "FirstOccupy": 900, "Occupy": 450, "FirstPersonalOccupy": 600, "PersonalOccupy": 300, "RuleShow": 1, "Describe": 912224, "BuffArray": ["20065;120"], "BuffArrayLength": 1, "BuffDic": {"20065": 120}, "WorldcityId": 0, "Index": 37},
    {"Id": 39, "Season": 2, "Name": 912223, "GroupName": 912099, "Group": 1, "BuildingSize": 2, "Prefab": "World_EarlyBattle_Hospital", "LodPic": "img_earlyBattle_yiyuan", "LodPicScale": 0, "LodIcon": "icon_chiji_yiyuan_01", "Icon": "lod_GW_City_yiyuan", "PosArray": [60, 1185], "PosArrayLength": 2, "FirstOccupyTime": 15, "OccupyTime": 5, "FirstOccupy": 900, "Occupy": 450, "FirstPersonalOccupy": 600, "PersonalOccupy": 300, "RuleShow": 1, "Describe": 912224, "BuffArray": ["20065;120"], "BuffArrayLength": 1, "BuffDic": {"20065": 120}, "WorldcityId": 0, "Index": 38},
    {"Id": 40, "Season": 3, "Name": 912085, "GroupName": 912101, "Group": 3, "BuildingSize": 8, "Prefab": "World_EarlyBattle_MineBig", "LodPic": "ResCitrine4", "LodPicScale": 0, "LodIcon": "lod_GW_City_dakuang", "Icon": "lod_GW_City_dakuang", "PosArray": [50, 1150], "PosArrayLength": 2, "FirstOccupyTime": 30, "OccupyTime": 10, "FirstOccupy": 9000, "Occupy": 6000, "FirstPersonalOccupy": 4500, "PersonalOccupy": 3000, "RuleShow": 1, "Describe": 912086, "BuffArray": null, "BuffArrayLength": 0, "BuffDic": {}, "WorldcityId": 0, "Index": 39},
    {"Id": 41, "Season": 3, "Name": 912087, "GroupName": 912099, "Group": 1, "BuildingSize": 2, "Prefab": "World_EarlyBattle_MineMid", "LodPic": "ResCitrine2", "LodPicScale": 0, "LodIcon": "lod_GW_City_zhongkuang", "Icon": "lod_GW_City_zhongkuang", "PosArray": [63, 1118], "PosArrayLength": 2, "FirstOccupyTime": 15, "OccupyTime": 5, "FirstOccupy": 4500, "Occupy": 2250, "FirstPersonalOccupy": 3000, "PersonalOccupy": 1500, "RuleShow": 1, "Describe": 912089, "BuffArray": null, "BuffArrayLength": 0, "BuffDic": {}, "WorldcityId": 0, "Index": 40},
    {"Id": 42, "Season": 3, "Name": 912088, "GroupName": 912099, "Group": 1, "BuildingSize": 2, "Prefab": "World_EarlyBattle_MineMid", "LodPic": "ResCitrine2", "LodPicScale": 0, "LodIcon": "lod_GW_City_zhongkuang", "Icon": "lod_GW_City_zhongkuang", "PosArray": [37, 1182], "PosArrayLength": 2, "FirstOccupyTime": 15, "OccupyTime": 5, "FirstOccupy": 4500, "Occupy": 2250, "FirstPersonalOccupy": 3000, "PersonalOccupy": 1500, "RuleShow": 1, "Describe": 912089, "BuffArray": null, "BuffArrayLength": 0, "BuffDic": {}, "WorldcityId": 0, "Index": 41},
    {"Id": 43, "Season": 3, "Name": 912090, "GroupName": 912099, "Group": 1, "BuildingSize": 1, "Prefab": "World_EarlyBattle_MineSmall", "LodPic": "ResCitrine1", "LodPicScale": 0, "LodIcon": "lod_GW_City_xiaokuang", "Icon": "lod_GW_City_xiaokuang", "PosArray": [82, 1137], "PosArrayLength": 2, "FirstOccupyTime": 15, "OccupyTime": 5, "FirstOccupy": 3000, "Occupy": 1500, "FirstPersonalOccupy": 2000, "PersonalOccupy": 1000, "RuleShow": 1, "Describe": 912092, "BuffArray": null, "BuffArrayLength": 0, "BuffDic": {}, "WorldcityId": 0, "Index": 42},
    {"Id": 44, "Season": 3, "Name": 912091, "GroupName": 912099, "Group": 1, "BuildingSize": 1, "Prefab": "World_EarlyBattle_MineSmall", "LodPic": "ResCitrine1", "LodPicScale": 0, "LodIcon": "lod_GW_City_xiaokuang", "Icon": "lod_GW_City_xiaokuang", "PosArray": [18, 1163], "PosArrayLength": 2, "FirstOccupyTime": 15, "OccupyTime": 5, "FirstOccupy": 3000, "Occupy": 1500, "FirstPersonalOccupy": 2000, "PersonalOccupy": 1000, "RuleShow": 1, "Describe": 912092, "BuffArray": null, "BuffArrayLength": 0, "BuffDic": {}, "WorldcityId": 0, "Index": 43},
    {"Id": 45, "Season": 3, "Name": 912093, "GroupName": 912099, "Group": 1, "BuildingSize": 2, "Prefab": "World_EarlyBattle_Radar", "LodPic": "img_earlyBattle_leida", "LodPicScale": 0, "LodIcon": "icon_chiji_leida_01", "Icon": "lod_GW_City_leida", "PosArray": [15, 1115], "PosArrayLength": 2, "FirstOccupyTime": 15, "OccupyTime": 5, "FirstOccupy": 900, "Occupy": 450, "FirstPersonalOccupy": 600, "PersonalOccupy": 300, "RuleShow": 1, "Describe": 912095, "BuffArray": ["10825;60", "60;50"], "BuffArrayLength": 2, "BuffDic": {"10825": 60, "60": 50}, "WorldcityId": 0, "Index": 44},
    {"Id": 46, "Season": 3, "Name": 912094, "GroupName": 912099, "Group": 1, "BuildingSize": 2, "Prefab": "World_EarlyBattle_Radar", "LodPic": "img_earlyBattle_leida", "LodPicScale": 0, "LodIcon": "icon_chiji_leida_01", "Icon": "lod_GW_City_leida", "PosArray": [85, 1185], "PosArrayLength": 2, "FirstOccupyTime": 15, "OccupyTime": 5, "FirstOccupy": 900, "Occupy": 450, "FirstPersonalOccupy": 600, "PersonalOccupy": 300, "RuleShow": 1, "Describe": 912095, "BuffArray": ["10825;60", "60;50"], "BuffArrayLength": 2, "BuffDic": {"10825": 60, "60": 50}, "WorldcityId": 0, "Index": 45},
    {"Id": 47, "Season": 3, "Name": 912096, "GroupName": 912100, "Group": 2, "BuildingSize": 2, "Prefab": "World_EarlyBattle_Combat", "LodPic": "img_earlyBattle_junhuo", "LodPicScale": 0, "LodIcon": "icon_chiji_junhuoku_01", "Icon": "lod_GW_City_zhanbei", "PosArray": [38, 1138], "PosArrayLength": 2, "FirstOccupyTime": 15, "OccupyTime": 5, "FirstOccupy": 900, "Occupy": 450, "FirstPersonalOccupy": 600, "PersonalOccupy": 300, "RuleShow": 1, "Describe": 912097, "BuffArray": ["20081;20"], "BuffArrayLength": 1, "BuffDic": {"20081": 20}, "WorldcityId": 0, "Index": 46},
    {"Id": 48, "Season": 3, "Name": 912218, "GroupName": 912100, "Group": 2, "BuildingSize": 2, "Prefab": "World_EarlyBattle_Defense", "LodPic": "img_earlyBattle_cheku", "LodPicScale": 0, "LodIcon": "icon_chiji_cheku_01", "Icon": "lod_GW_City_fangbei", "PosArray": [62, 1162], "PosArrayLength": 2, "FirstOccupyTime": 15, "OccupyTime": 5, "FirstOccupy": 900, "Occupy": 450, "FirstPersonalOccupy": 600, "PersonalOccupy": 300, "RuleShow": 1, "Describe": 912219, "BuffArray": ["20082;20"], "BuffArrayLength": 1, "BuffDic": {"20082": 20}, "WorldcityId": 0, "Index": 47},
    {"Id": 49, "Season": 3, "Name": 912220, "GroupName": 912099, "Group": 1, "BuildingSize": 2, "Prefab": "World_EarlyBattle_Hospital", "LodPic": "img_earlyBattle_yiyuan", "LodPicScale": 0, "LodIcon": "icon_chiji_yiyuan_01", "Icon": "lod_GW_City_yiyuan", "PosArray": [40, 1115], "PosArrayLength": 2, "FirstOccupyTime": 15, "OccupyTime": 5, "FirstOccupy": 900, "Occupy": 450, "FirstPersonalOccupy": 600, "PersonalOccupy": 300, "RuleShow": 1, "Describe": 912224, "BuffArray": ["20065;120"], "BuffArrayLength": 1, "BuffDic": {"20065": 120}, "WorldcityId": 0, "Index": 48},
    {"Id": 50, "Season": 3, "Name": 912221, "GroupName": 912099, "Group": 1, "BuildingSize": 2, "Prefab": "World_EarlyBattle_Hospital", "LodPic": "img_earlyBattle_yiyuan", "LodPicScale": 0, "LodIcon": "icon_chiji_yiyuan_01", "Icon": "lod_GW_City_yiyuan", "PosArray": [15, 1140], "PosArrayLength": 2, "FirstOccupyTime": 15, "OccupyTime": 5, "FirstOccupy": 900, "Occupy": 450, "FirstPersonalOccupy": 600, "PersonalOccupy": 300, "RuleShow": 1, "Describe": 912224, "BuffArray": ["20065;120"], "BuffArrayLength": 1, "BuffDic": {"20065": 120}, "WorldcityId": 0, "Index": 49},
    {"Id": 51, "Season": 3, "Name": 912222, "GroupName": 912099, "Group": 1, "BuildingSize": 2, "Prefab": "World_EarlyBattle_Hospital", "LodPic": "img_earlyBattle_yiyuan", "LodPicScale": 0, "LodIcon": "icon_chiji_yiyuan_01", "Icon": "lod_GW_City_yiyuan", "PosArray": [85, 1160], "PosArrayLength": 2, "FirstOccupyTime": 15, "OccupyTime": 5, "FirstOccupy": 900, "Occupy": 450, "FirstPersonalOccupy": 600, "PersonalOccupy": 300, "RuleShow": 1, "Describe": 912224, "BuffArray": ["20065;120"], "BuffArrayLength": 1, "BuffDic": {"20065": 120}, "WorldcityId": 0, "Index": 50},
    {"Id": 52, "Season": 3, "Name": 912223, "GroupName": 912099, "Group": 1, "BuildingSize": 2, "Prefab": "World_EarlyBattle_Hospital", "LodPic": "img_earlyBattle_yiyuan", "LodPicScale": 0, "LodIcon": "icon_chiji_yiyuan_01", "Icon": "lod_GW_City_yiyuan", "PosArray": [60, 1185], "PosArrayLength": 2, "FirstOccupyTime": 15, "OccupyTime": 5, "FirstOccupy": 900, "Occupy": 450, "FirstPersonalOccupy": 600, "PersonalOccupy": 300, "RuleShow": 1, "Describe": 912224, "BuffArray": ["20065;120"], "BuffArrayLength": 1, "BuffDic": {"20065": 120}, "WorldcityId": 0, "Index": 51},
    {"Id": 53, "Season": 4, "Name": 912085, "GroupName": 912101, "Group": 3, "BuildingSize": 8, "Prefab": "World_EarlyBattle_MineBig", "LodPic": "ResCitrine4", "LodPicScale": 0, "LodIcon": "lod_GW_City_dakuang", "Icon": "lod_GW_City_dakuang", "PosArray": [50, 1150], "PosArrayLength": 2, "FirstOccupyTime": 30, "OccupyTime": 10, "FirstOccupy": 9000, "Occupy": 6000, "FirstPersonalOccupy": 4500, "PersonalOccupy": 3000, "RuleShow": 1, "Describe": 912086, "BuffArray": null, "BuffArrayLength": 0, "BuffDic": {}, "WorldcityId": 0, "Index": 52},
    {"Id": 54, "Season": 4, "Name": 912087, "GroupName": 912099, "Group": 1, "BuildingSize": 2, "Prefab": "World_EarlyBattle_MineMid", "LodPic": "ResCitrine2", "LodPicScale": 0, "LodIcon": "lod_GW_City_zhongkuang", "Icon": "lod_GW_City_zhongkuang", "PosArray": [63, 1118], "PosArrayLength": 2, "FirstOccupyTime": 15, "OccupyTime": 5, "FirstOccupy": 4500, "Occupy": 2250, "FirstPersonalOccupy": 3000, "PersonalOccupy": 1500, "RuleShow": 1, "Describe": 912089, "BuffArray": null, "BuffArrayLength": 0, "BuffDic": {}, "WorldcityId": 0, "Index": 53},
    {"Id": 55, "Season": 4, "Name": 912088, "GroupName": 912099, "Group": 1, "BuildingSize": 2, "Prefab": "World_EarlyBattle_MineMid", "LodPic": "ResCitrine2", "LodPicScale": 0, "LodIcon": "lod_GW_City_zhongkuang", "Icon": "lod_GW_City_zhongkuang", "PosArray": [37, 1182], "PosArrayLength": 2, "FirstOccupyTime": 15, "OccupyTime": 5, "FirstOccupy": 4500, "Occupy": 2250, "FirstPersonalOccupy": 3000, "PersonalOccupy": 1500, "RuleShow": 1, "Describe": 912089, "BuffArray": null, "BuffArrayLength": 0, "BuffDic": {}, "WorldcityId": 0, "Index": 54},
    {"Id": 56, "Season": 4, "Name": 912090, "GroupName": 912099, "Group": 1, "BuildingSize": 1, "Prefab": "World_EarlyBattle_MineSmall", "LodPic": "ResCitrine1", "LodPicScale": 0, "LodIcon": "lod_GW_City_xiaokuang", "Icon": "lod_GW_City_xiaokuang", "PosArray": [82, 1137], "PosArrayLength": 2, "FirstOccupyTime": 15, "OccupyTime": 5, "FirstOccupy": 3000, "Occupy": 1500, "FirstPersonalOccupy": 2000, "PersonalOccupy": 1000, "RuleShow": 1, "Describe": 912092, "BuffArray": null, "BuffArrayLength": 0, "BuffDic": {}, "WorldcityId": 0, "Index": 55},
    {"Id": 57, "Season": 4, "Name": 912091, "GroupName": 912099, "Group": 1, "BuildingSize": 1, "Prefab": "World_EarlyBattle_MineSmall", "LodPic": "ResCitrine1", "LodPicScale": 0, "LodIcon": "lod_GW_City_xiaokuang", "Icon": "lod_GW_City_xiaokuang", "PosArray": [18, 1163], "PosArrayLength": 2, "FirstOccupyTime": 15, "OccupyTime": 5, "FirstOccupy": 3000, "Occupy": 1500, "FirstPersonalOccupy": 2000, "PersonalOccupy": 1000, "RuleShow": 1, "Describe": 912092, "BuffArray": null, "BuffArrayLength": 0, "BuffDic": {}, "WorldcityId": 0, "Index": 56},
    {"Id": 58, "Season": 4, "Name": 912093, "GroupName": 912099, "Group": 1, "BuildingSize": 2, "Prefab": "World_EarlyBattle_Radar", "LodPic": "img_earlyBattle_leida", "LodPicScale": 0, "LodIcon": "icon_chiji_leida_01", "Icon": "lod_GW_City_leida", "PosArray": [15, 1115], "PosArrayLength": 2, "FirstOccupyTime": 15, "OccupyTime": 5, "FirstOccupy": 900, "Occupy": 450, "FirstPersonalOccupy": 600, "PersonalOccupy": 300, "RuleShow": 1, "Describe": 912095, "BuffArray": ["10825;60", "60;50"], "BuffArrayLength": 2, "BuffDic": {"10825": 60, "60": 50}, "WorldcityId": 0, "Index": 57},
    {"Id": 59, "Season": 4, "Name": 912094, "GroupName": 912099, "Group": 1, "BuildingSize": 2, "Prefab": "World_EarlyBattle_Radar", "LodPic": "img_earlyBattle_leida", "LodPicScale": 0, "LodIcon": "icon_chiji_leida_01", "Icon": "lod_GW_City_leida", "PosArray": [85, 1185], "PosArrayLength": 2, "FirstOccupyTime": 15, "OccupyTime": 5, "FirstOccupy": 900, "Occupy": 450, "FirstPersonalOccupy": 600, "PersonalOccupy": 300, "RuleShow": 1, "Describe": 912095, "BuffArray": ["10825;60", "60;50"], "BuffArrayLength": 2, "BuffDic": {"10825": 60, "60": 50}, "WorldcityId": 0, "Index": 58},
    {"Id": 60, "Season": 4, "Name": 912096, "GroupName": 912100, "Group": 2, "BuildingSize": 2, "Prefab": "World_EarlyBattle_Combat", "LodPic": "img_earlyBattle_junhuo", "LodPicScale": 0, "LodIcon": "icon_chiji_junhuoku_01", "Icon": "lod_GW_City_zhanbei", "PosArray": [38, 1138], "PosArrayLength": 2, "FirstOccupyTime": 15, "OccupyTime": 5, "FirstOccupy": 900, "Occupy": 450, "FirstPersonalOccupy": 600, "PersonalOccupy": 300, "RuleShow": 1, "Describe": 912097, "BuffArray": ["20081;20"], "BuffArrayLength": 1, "BuffDic": {"20081": 20}, "WorldcityId": 0, "Index": 59},
    {"Id": 61, "Season": 4, "Name": 912218, "GroupName": 912100, "Group": 2, "BuildingSize": 2, "Prefab": "World_EarlyBattle_Defense", "LodPic": "img_earlyBattle_cheku", "LodPicScale": 0, "LodIcon": "icon_chiji_cheku_01", "Icon": "lod_GW_City_fangbei", "PosArray": [62, 1162], "PosArrayLength": 2, "FirstOccupyTime": 15, "OccupyTime": 5, "FirstOccupy": 900, "Occupy": 450, "FirstPersonalOccupy": 600, "PersonalOccupy": 300, "RuleShow": 1, "Describe": 912219, "BuffArray": ["20082;20"], "BuffArrayLength": 1, "BuffDic": {"20082": 20}, "WorldcityId": 0, "Index": 60},
    {"Id": 62, "Season": 4, "Name": 912220, "GroupName": 912099, "Group": 1, "BuildingSize": 2, "Prefab": "World_EarlyBattle_Hospital", "LodPic": "img_earlyBattle_yiyuan", "LodPicScale": 0, "LodIcon": "icon_chiji_yiyuan_01", "Icon": "lod_GW_City_yiyuan", "PosArray": [40, 1115], "PosArrayLength": 2, "FirstOccupyTime": 15, "OccupyTime": 5, "FirstOccupy": 900, "Occupy": 450, "FirstPersonalOccupy": 600, "PersonalOccupy": 300, "RuleShow": 1, "Describe": 912224, "BuffArray": ["20065;120"], "BuffArrayLength": 1, "BuffDic": {"20065": 120}, "WorldcityId": 0, "Index": 61},
    {"Id": 63, "Season": 4, "Name": 912221, "GroupName": 912099, "Group": 1, "BuildingSize": 2, "Prefab": "World_EarlyBattle_Hospital", "LodPic": "img_earlyBattle_yiyuan", "LodPicScale": 0, "LodIcon": "icon_chiji_yiyuan_01", "Icon": "lod_GW_City_yiyuan", "PosArray": [15, 1140], "PosArrayLength": 2, "FirstOccupyTime": 15, "OccupyTime": 5, "FirstOccupy": 900, "Occupy": 450, "FirstPersonalOccupy": 600, "PersonalOccupy": 300, "RuleShow": 1, "Describe": 912224, "BuffArray": ["20065;120"], "BuffArrayLength": 1, "BuffDic": {"20065": 120}, "WorldcityId": 0, "Index": 62},
    {"Id": 64, "Season": 4, "Name": 912222, "GroupName": 912099, "Group": 1, "BuildingSize": 2, "Prefab": "World_EarlyBattle_Hospital", "LodPic": "img_earlyBattle_yiyuan", "LodPicScale": 0, "LodIcon": "icon_chiji_yiyuan_01", "Icon": "lod_GW_City_yiyuan", "PosArray": [85, 1160], "PosArrayLength": 2, "FirstOccupyTime": 15, "OccupyTime": 5, "FirstOccupy": 900, "Occupy": 450, "FirstPersonalOccupy": 600, "PersonalOccupy": 300, "RuleShow": 1, "Describe": 912224, "BuffArray": ["20065;120"], "BuffArrayLength": 1, "BuffDic": {"20065": 120}, "WorldcityId": 0, "Index": 63},
    {"Id": 65, "Season": 4, "Name": 912223, "GroupName": 912099, "Group": 1, "BuildingSize": 2, "Prefab": "World_EarlyBattle_Hospital", "LodPic": "img_earlyBattle_yiyuan", "LodPicScale": 0, "LodIcon": "icon_chiji_yiyuan_01", "Icon": "lod_GW_City_yiyuan", "PosArray": [60, 1185], "PosArrayLength": 2, "FirstOccupyTime": 15, "OccupyTime": 5, "FirstOccupy": 900, "Occupy": 450, "FirstPersonalOccupy": 600, "PersonalOccupy": 300, "RuleShow": 1, "Describe": 912224, "BuffArray": ["20065;120"], "BuffArrayLength": 1, "BuffDic": {"20065": 120}, "WorldcityId": 0, "Index": 64},
    {"Id": 66, "Season": 5, "Name": 912085, "GroupName": 912101, "Group": 3, "BuildingSize": 8, "Prefab": "World_EarlyBattle_MineBig", "LodPic": "ResCitrine4", "LodPicScale": 0, "LodIcon": "lod_GW_City_dakuang", "Icon": "lod_GW_City_dakuang", "PosArray": [50, 1150], "PosArrayLength": 2, "FirstOccupyTime": 30, "OccupyTime": 10, "FirstOccupy": 9000, "Occupy": 6000, "FirstPersonalOccupy": 4500, "PersonalOccupy": 3000, "RuleShow": 1, "Describe": 912086, "BuffArray": null, "BuffArrayLength": 0, "BuffDic": {}, "WorldcityId": 0, "Index": 65},
    {"Id": 67, "Season": 5, "Name": 912087, "GroupName": 912099, "Group": 1, "BuildingSize": 2, "Prefab": "World_EarlyBattle_MineMid", "LodPic": "ResCitrine2", "LodPicScale": 0, "LodIcon": "lod_GW_City_zhongkuang", "Icon": "lod_GW_City_zhongkuang", "PosArray": [63, 1118], "PosArrayLength": 2, "FirstOccupyTime": 15, "OccupyTime": 5, "FirstOccupy": 4500, "Occupy": 2250, "FirstPersonalOccupy": 3000, "PersonalOccupy": 1500, "RuleShow": 1, "Describe": 912089, "BuffArray": null, "BuffArrayLength": 0, "BuffDic": {}, "WorldcityId": 0, "Index": 66},
    {"Id": 68, "Season": 5, "Name": 912088, "GroupName": 912099, "Group": 1, "BuildingSize": 2, "Prefab": "World_EarlyBattle_MineMid", "LodPic": "ResCitrine2", "LodPicScale": 0, "LodIcon": "lod_GW_City_zhongkuang", "Icon": "lod_GW_City_zhongkuang", "PosArray": [37, 1182], "PosArrayLength": 2, "FirstOccupyTime": 15, "OccupyTime": 5, "FirstOccupy": 4500, "Occupy": 2250, "FirstPersonalOccupy": 3000, "PersonalOccupy": 1500, "RuleShow": 1, "Describe": 912089, "BuffArray": null, "BuffArrayLength": 0, "BuffDic": {}, "WorldcityId": 0, "Index": 67},
    {"Id": 69, "Season": 5, "Name": 912090, "GroupName": 912099, "Group": 1, "BuildingSize": 1, "Prefab": "World_EarlyBattle_MineSmall", "LodPic": "ResCitrine1", "LodPicScale": 0, "LodIcon": "lod_GW_City_xiaokuang", "Icon": "lod_GW_City_xiaokuang", "PosArray": [82, 1137], "PosArrayLength": 2, "FirstOccupyTime": 15, "OccupyTime": 5, "FirstOccupy": 3000, "Occupy": 1500, "FirstPersonalOccupy": 2000, "PersonalOccupy": 1000, "RuleShow": 1, "Describe": 912092, "BuffArray": null, "BuffArrayLength": 0, "BuffDic": {}, "WorldcityId": 0, "Index": 68},
    {"Id": 70, "Season": 5, "Name": 912091, "GroupName": 912099, "Group": 1, "BuildingSize": 1, "Prefab": "World_EarlyBattle_MineSmall", "LodPic": "ResCitrine1", "LodPicScale": 0, "LodIcon": "lod_GW_City_xiaokuang", "Icon": "lod_GW_City_xiaokuang", "PosArray": [18, 1163], "PosArrayLength": 2, "FirstOccupyTime": 15, "OccupyTime": 5, "FirstOccupy": 3000, "Occupy": 1500, "FirstPersonalOccupy": 2000, "PersonalOccupy": 1000, "RuleShow": 1, "Describe": 912092, "BuffArray": null, "BuffArrayLength": 0, "BuffDic": {}, "WorldcityId": 0, "Index": 69},
    {"Id": 71, "Season": 5, "Name": 912093, "GroupName": 912099, "Group": 1, "BuildingSize": 2, "Prefab": "World_EarlyBattle_Radar", "LodPic": "img_earlyBattle_leida", "LodPicScale": 0, "LodIcon": "icon_chiji_leida_01", "Icon": "lod_GW_City_leida", "PosArray": [15, 1115], "PosArrayLength": 2, "FirstOccupyTime": 15, "OccupyTime": 5, "FirstOccupy": 900, "Occupy": 450, "FirstPersonalOccupy": 600, "PersonalOccupy": 300, "RuleShow": 1, "Describe": 912095, "BuffArray": ["10825;60", "60;50"], "BuffArrayLength": 2, "BuffDic": {"10825": 60, "60": 50}, "WorldcityId": 0, "Index": 70},
    {"Id": 72, "Season": 5, "Name": 912094, "GroupName": 912099, "Group": 1, "BuildingSize": 2, "Prefab": "World_EarlyBattle_Radar", "LodPic": "img_earlyBattle_leida", "LodPicScale": 0, "LodIcon": "icon_chiji_leida_01", "Icon": "lod_GW_City_leida", "PosArray": [85, 1185], "PosArrayLength": 2, "FirstOccupyTime": 15, "OccupyTime": 5, "FirstOccupy": 900, "Occupy": 450, "FirstPersonalOccupy": 600, "PersonalOccupy": 300, "RuleShow": 1, "Describe": 912095, "BuffArray": ["10825;60", "60;50"], "BuffArrayLength": 2, "BuffDic": {"10825": 60, "60": 50}, "WorldcityId": 0, "Index": 71},
    {"Id": 73, "Season": 5, "Name": 912096, "GroupName": 912100, "Group": 2, "BuildingSize": 2, "Prefab": "World_EarlyBattle_Combat", "LodPic": "img_earlyBattle_junhuo", "LodPicScale": 0, "LodIcon": "icon_chiji_junhuoku_01", "Icon": "lod_GW_City_zhanbei", "PosArray": [38, 1138], "PosArrayLength": 2, "FirstOccupyTime": 15, "OccupyTime": 5, "FirstOccupy": 900, "Occupy": 450, "FirstPersonalOccupy": 600, "PersonalOccupy": 300, "RuleShow": 1, "Describe": 912097, "BuffArray": ["20081;20"], "BuffArrayLength": 1, "BuffDic": {"20081": 20}, "WorldcityId": 0, "Index": 72},
    {"Id": 74, "Season": 5, "Name": 912218, "GroupName": 912100, "Group": 2, "BuildingSize": 2, "Prefab": "World_EarlyBattle_Defense", "LodPic": "img_earlyBattle_cheku", "LodPicScale": 0, "LodIcon": "icon_chiji_cheku_01", "Icon": "lod_GW_City_fangbei", "PosArray": [62, 1162], "PosArrayLength": 2, "FirstOccupyTime": 15, "OccupyTime": 5, "FirstOccupy": 900, "Occupy": 450, "FirstPersonalOccupy": 600, "PersonalOccupy": 300, "RuleShow": 1, "Describe": 912219, "BuffArray": ["20082;20"], "BuffArrayLength": 1, "BuffDic": {"20082": 20}, "WorldcityId": 0, "Index": 73},
    {"Id": 75, "Season": 5, "Name": 912220, "GroupName": 912099, "Group": 1, "BuildingSize": 2, "Prefab": "World_EarlyBattle_Hospital", "LodPic": "img_earlyBattle_yiyuan", "LodPicScale": 0, "LodIcon": "icon_chiji_yiyuan_01", "Icon": "lod_GW_City_yiyuan", "PosArray": [40, 1115], "PosArrayLength": 2, "FirstOccupyTime": 15, "OccupyTime": 5, "FirstOccupy": 900, "Occupy": 450, "FirstPersonalOccupy": 600, "PersonalOccupy": 300, "RuleShow": 1, "Describe": 912224, "BuffArray": ["20065;120"], "BuffArrayLength": 1, "BuffDic": {"20065": 120}, "WorldcityId": 0, "Index": 74},
    {"Id": 76, "Season": 5, "Name": 912221, "GroupName": 912099, "Group": 1, "BuildingSize": 2, "Prefab": "World_EarlyBattle_Hospital", "LodPic": "img_earlyBattle_yiyuan", "LodPicScale": 0, "LodIcon": "icon_chiji_yiyuan_01", "Icon": "lod_GW_City_yiyuan", "PosArray": [15, 1140], "PosArrayLength": 2, "FirstOccupyTime": 15, "OccupyTime": 5, "FirstOccupy": 900, "Occupy": 450, "FirstPersonalOccupy": 600, "PersonalOccupy": 300, "RuleShow": 1, "Describe": 912224, "BuffArray": ["20065;120"], "BuffArrayLength": 1, "BuffDic": {"20065": 120}, "WorldcityId": 0, "Index": 75},
    {"Id": 77, "Season": 5, "Name": 912222, "GroupName": 912099, "Group": 1, "BuildingSize": 2, "Prefab": "World_EarlyBattle_Hospital", "LodPic": "img_earlyBattle_yiyuan", "LodPicScale": 0, "LodIcon": "icon_chiji_yiyuan_01", "Icon": "lod_GW_City_yiyuan", "PosArray": [85, 1160], "PosArrayLength": 2, "FirstOccupyTime": 15, "OccupyTime": 5, "FirstOccupy": 900, "Occupy": 450, "FirstPersonalOccupy": 600, "PersonalOccupy": 300, "RuleShow": 1, "Describe": 912224, "BuffArray": ["20065;120"], "BuffArrayLength": 1, "BuffDic": {"20065": 120}, "WorldcityId": 0, "Index": 76},
    {"Id": 78, "Season": 5, "Name": 912223, "GroupName": 912099, "Group": 1, "BuildingSize": 2, "Prefab": "World_EarlyBattle_Hospital", "LodPic": "img_earlyBattle_yiyuan", "LodPicScale": 0, "LodIcon": "icon_chiji_yiyuan_01", "Icon": "lod_GW_City_yiyuan", "PosArray": [60, 1185], "PosArrayLength": 2, "FirstOccupyTime": 15, "OccupyTime": 5, "FirstOccupy": 900, "Occupy": 450, "FirstPersonalOccupy": 600, "PersonalOccupy": 300, "RuleShow": 1, "Describe": 912224, "BuffArray": ["20065;120"], "BuffArrayLength": 1, "BuffDic": {"20065": 120}, "WorldcityId": 0, "Index": 77},
    {"Id": 201, "Season": 6, "Name": 912085, "GroupName": 912101, "Group": 3, "BuildingSize": 8, "Prefab": "World_EarlyBattle_MineBig", "LodPic": "ResCitrine4", "LodPicScale": 0, "LodIcon": "lod_GW_City_dakuang", "Icon": "lod_GW_City_dakuang", "PosArray": [50, 1150], "PosArrayLength": 2, "FirstOccupyTime": 30, "OccupyTime": 10, "FirstOccupy": 9000, "Occupy": 6000, "FirstPersonalOccupy": 4500, "PersonalOccupy": 3000, "RuleShow": 1, "Describe": 912086, "BuffArray": null, "BuffArrayLength": 0, "BuffDic": {}, "WorldcityId": 0, "Index": 78},
    {"Id": 202, "Season": 6, "Name": 912087, "GroupName": 912099, "Group": 1, "BuildingSize": 2, "Prefab": "World_EarlyBattle_MineMid", "LodPic": "ResCitrine2", "LodPicScale": 0, "LodIcon": "lod_GW_City_zhongkuang", "Icon": "lod_GW_City_zhongkuang", "PosArray": [63, 1118], "PosArrayLength": 2, "FirstOccupyTime": 15, "OccupyTime": 5, "FirstOccupy": 4500, "Occupy": 2250, "FirstPersonalOccupy": 3000, "PersonalOccupy": 1500, "RuleShow": 1, "Describe": 912089, "BuffArray": null, "BuffArrayLength": 0, "BuffDic": {}, "WorldcityId": 0, "Index": 79},
    {"Id": 203, "Season": 6, "Name": 912088, "GroupName": 912099, "Group": 1, "BuildingSize": 2, "Prefab": "World_EarlyBattle_MineMid", "LodPic": "ResCitrine2", "LodPicScale": 0, "LodIcon": "lod_GW_City_zhongkuang", "Icon": "lod_GW_City_zhongkuang", "PosArray": [37, 1182], "PosArrayLength": 2, "FirstOccupyTime": 15, "OccupyTime": 5, "FirstOccupy": 4500, "Occupy": 2250, "FirstPersonalOccupy": 3000, "PersonalOccupy": 1500, "RuleShow": 1, "Describe": 912089, "BuffArray": null, "BuffArrayLength": 0, "BuffDic": {}, "WorldcityId": 0, "Index": 80},
    {"Id": 204, "Season": 6, "Name": 912090, "GroupName": 912099, "Group": 1, "BuildingSize": 1, "Prefab": "World_EarlyBattle_MineSmall", "LodPic": "ResCitrine1", "LodPicScale": 0, "LodIcon": "lod_GW_City_xiaokuang", "Icon": "lod_GW_City_xiaokuang", "PosArray": [82, 1137], "PosArrayLength": 2, "FirstOccupyTime": 15, "OccupyTime": 5, "FirstOccupy": 3000, "Occupy": 1500, "FirstPersonalOccupy": 2000, "PersonalOccupy": 1000, "RuleShow": 1, "Describe": 912092, "BuffArray": null, "BuffArrayLength": 0, "BuffDic": {}, "WorldcityId": 0, "Index": 81},
    {"Id": 205, "Season": 6, "Name": 912091, "GroupName": 912099, "Group": 1, "BuildingSize": 1, "Prefab": "World_EarlyBattle_MineSmall", "LodPic": "ResCitrine1", "LodPicScale": 0, "LodIcon": "lod_GW_City_xiaokuang", "Icon": "lod_GW_City_xiaokuang", "PosArray": [18, 1163], "PosArrayLength": 2, "FirstOccupyTime": 15, "OccupyTime": 5, "FirstOccupy": 3000, "Occupy": 1500, "FirstPersonalOccupy": 2000, "PersonalOccupy": 1000, "RuleShow": 1, "Describe": 912092, "BuffArray": null, "BuffArrayLength": 0, "BuffDic": {}, "WorldcityId": 0, "Index": 82},
    {"Id": 206, "Season": 6, "Name": 912093, "GroupName": 912099, "Group": 1, "BuildingSize": 2, "Prefab": "World_EarlyBattle_Radar", "LodPic": "img_earlyBattle_leida", "LodPicScale": 0, "LodIcon": "icon_chiji_leida_01", "Icon": "lod_GW_City_leida", "PosArray": [15, 1115], "PosArrayLength": 2, "FirstOccupyTime": 15, "OccupyTime": 5, "FirstOccupy": 900, "Occupy": 450, "FirstPersonalOccupy": 600, "PersonalOccupy": 300, "RuleShow": 1, "Describe": 912095, "BuffArray": ["10825;60", "60;50"], "BuffArrayLength": 2, "BuffDic": {"10825": 60, "60": 50}, "WorldcityId": 0, "Index": 83},
    {"Id": 207, "Season": 6, "Name": 912094, "GroupName": 912099, "Group": 1, "BuildingSize": 2, "Prefab": "World_EarlyBattle_Radar", "LodPic": "img_earlyBattle_leida", "LodPicScale": 0, "LodIcon": "icon_chiji_leida_01", "Icon": "lod_GW_City_leida", "PosArray": [85, 1185], "PosArrayLength": 2, "FirstOccupyTime": 15, "OccupyTime": 5, "FirstOccupy": 900, "Occupy": 450, "FirstPersonalOccupy": 600, "PersonalOccupy": 300, "RuleShow": 1, "Describe": 912095, "BuffArray": ["10825;60", "60;50"], "BuffArrayLength": 2, "BuffDic": {"10825": 60, "60": 50}, "WorldcityId": 0, "Index": 84},
    {"Id": 208, "Season": 6, "Name": 912096, "GroupName": 912100, "Group": 2, "BuildingSize": 2, "Prefab": "World_EarlyBattle_Combat", "LodPic": "img_earlyBattle_junhuo", "LodPicScale": 0, "LodIcon": "icon_chiji_junhuoku_01", "Icon": "lod_GW_City_zhanbei", "PosArray": [38, 1138], "PosArrayLength": 2, "FirstOccupyTime": 15, "OccupyTime": 5, "FirstOccupy": 900, "Occupy": 450, "FirstPersonalOccupy": 600, "PersonalOccupy": 300, "RuleShow": 1, "Describe": 912097, "BuffArray": ["20081;20"], "BuffArrayLength": 1, "BuffDic": {"20081": 20}, "WorldcityId": 0, "Index": 85},
    {"Id": 209, "Season": 6, "Name": 912218, "GroupName": 912100, "Group": 2, "BuildingSize": 2, "Prefab": "World_EarlyBattle_Defense", "LodPic": "img_earlyBattle_cheku", "LodPicScale": 0, "LodIcon": "icon_chiji_cheku_01", "Icon": "lod_GW_City_fangbei", "PosArray": [62, 1162], "PosArrayLength": 2, "FirstOccupyTime": 15, "OccupyTime": 5, "FirstOccupy": 900, "Occupy": 450, "FirstPersonalOccupy": 600, "PersonalOccupy": 300, "RuleShow": 1, "Describe": 912219, "BuffArray": ["20082;20"], "BuffArrayLength": 1, "BuffDic": {"20082": 20}, "WorldcityId": 0, "Index": 86},
    {"Id": 210, "Season": 6, "Name": 912220, "GroupName": 912099, "Group": 1, "BuildingSize": 2, "Prefab": "World_EarlyBattle_Hospital", "LodPic": "img_earlyBattle_yiyuan", "LodPicScale": 0, "LodIcon": "icon_chiji_yiyuan_01", "Icon": "lod_GW_City_yiyuan", "PosArray": [40, 1115], "PosArrayLength": 2, "FirstOccupyTime": 15, "OccupyTime": 5, "FirstOccupy": 900, "Occupy": 450, "FirstPersonalOccupy": 600, "PersonalOccupy": 300, "RuleShow": 1, "Describe": 912224, "BuffArray": ["20065;120"], "BuffArrayLength": 1, "BuffDic": {"20065": 120}, "WorldcityId": 0, "Index": 87},
    {"Id": 211, "Season": 6, "Name": 912221, "GroupName": 912099, "Group": 1, "BuildingSize": 2, "Prefab": "World_EarlyBattle_Hospital", "LodPic": "img_earlyBattle_yiyuan", "LodPicScale": 0, "LodIcon": "icon_chiji_yiyuan_01", "Icon": "lod_GW_City_yiyuan", "PosArray": [15, 1140], "PosArrayLength": 2, "FirstOccupyTime": 15, "OccupyTime": 5, "FirstOccupy": 900, "Occupy": 450, "FirstPersonalOccupy": 600, "PersonalOccupy": 300, "RuleShow": 1, "Describe": 912224, "BuffArray": ["20065;120"], "BuffArrayLength": 1, "BuffDic": {"20065": 120}, "WorldcityId": 0, "Index": 88},
    {"Id": 212, "Season": 6, "Name": 912222, "GroupName": 912099, "Group": 1, "BuildingSize": 2, "Prefab": "World_EarlyBattle_Hospital", "LodPic": "img_earlyBattle_yiyuan", "LodPicScale": 0, "LodIcon": "icon_chiji_yiyuan_01", "Icon": "lod_GW_City_yiyuan", "PosArray": [85, 1160], "PosArrayLength": 2, "FirstOccupyTime": 15, "OccupyTime": 5, "FirstOccupy": 900, "Occupy": 450, "FirstPersonalOccupy": 600, "PersonalOccupy": 300, "RuleShow": 1, "Describe": 912224, "BuffArray": ["20065;120"], "BuffArrayLength": 1, "BuffDic": {"20065": 120}, "WorldcityId": 0, "Index": 89},
    {"Id": 213, "Season": 6, "Name": 912223, "GroupName": 912099, "Group": 1, "BuildingSize": 2, "Prefab": "World_EarlyBattle_Hospital", "LodPic": "img_earlyBattle_yiyuan", "LodPicScale": 0, "LodIcon": "icon_chiji_yiyuan_01", "Icon": "lod_GW_City_yiyuan", "PosArray": [60, 1185], "PosArrayLength": 2, "FirstOccupyTime": 15, "OccupyTime": 5, "FirstOccupy": 900, "Occupy": 450, "FirstPersonalOccupy": 600, "PersonalOccupy": 300, "RuleShow": 1, "Describe": 912224, "BuffArray": ["20065;120"], "BuffArrayLength": 1, "BuffDic": {"20065": 120}, "WorldcityId": 0, "Index": 90}
  ]
}
