{
  "table_name": "Season_analyzerTable",
  "row_count": 4,
  "data": [
    {"Id": 1001, "Type": 1, "UnlockArray": [], "UnlockArrayLength": 0, "Name": 398814, "Description": 398900, "LimitNum": 30, "Desc": 398888, "Prefab": "bg_shiyanshi_jingshi_02", "TimeAnalyzerArray": ["200901;1800", "200902;3600"], "TimeAnalyzerArrayLength": 2, "TimeAnalyzerDic": {"200901": 1800, "200902": 3600}, "UnlockTypeArray": null, "UnlockTypeArrayLength": 0, "UnlockTypeDic": {}, "UnlockCostArray": null, "UnlockCostArrayLength": 0, "UnlockCostDic": {}, "Story": 5, "Season": -1, "Status": 0, "Index": 0},
    {"Id": 1002, "Type": 1, "UnlockArray": [2, 0], "UnlockArrayLength": 2, "Name": 398815, "Description": 398900, "LimitNum": 30, "Desc": 398888, "Prefab": "bg_shiyanshi_jingshi_03", "TimeAnalyzerArray": ["200901;1800", "200902;3600"], "TimeAnalyzerArrayLength": 2, "TimeAnalyzerDic": {"200901": 1800, "200902": 3600}, "UnlockTypeArray": ["1;1101", "2;100", "3;103008"], "UnlockTypeArrayLength": 3, "UnlockTypeDic": {"1": 1101, "2": 100, "3": 103008}, "UnlockCostArray": ["200903;300", "200904;1"], "UnlockCostArrayLength": 2, "UnlockCostDic": {"200903": 300, "200904": 1}, "Story": 5, "Season": -1, "Status": 0, "Index": 1},
    {"Id": 1003, "Type": 1, "UnlockArray": [2, 0], "UnlockArrayLength": 2, "Name": 398816, "Description": 398900, "LimitNum": 30, "Desc": 398888, "Prefab": "bg_shiyanshi_jingshi_04", "TimeAnalyzerArray": ["200901;1800", "200902;3600"], "TimeAnalyzerArrayLength": 2, "TimeAnalyzerDic": {"200901": 1800, "200902": 3600}, "UnlockTypeArray": ["1;1101", "2;100", "3;104008"], "UnlockTypeArrayLength": 3, "UnlockTypeDic": {"1": 1101, "2": 100, "3": 104008}, "UnlockCostArray": ["200903;600", "200904;1"], "UnlockCostArrayLength": 2, "UnlockCostDic": {"200903": 600, "200904": 1}, "Story": 5, "Season": -1, "Status": 0, "Index": 2},
    {"Id": 1004, "Type": 1, "UnlockArray": [1, 9021], "UnlockArrayLength": 2, "Name": 398955, "Description": 398900, "LimitNum": 30, "Desc": 398888, "Prefab": "bg_shiyanshi_jingshi_05", "TimeAnalyzerArray": ["200901;1800", "200902;3600"], "TimeAnalyzerArrayLength": 2, "TimeAnalyzerDic": {"200901": 1800, "200902": 3600}, "UnlockTypeArray": null, "UnlockTypeArrayLength": 0, "UnlockTypeDic": {}, "UnlockCostArray": null, "UnlockCostArrayLength": 0, "UnlockCostDic": {}, "Story": 5, "Season": -1, "Status": 501001, "Index": 3}
  ]
}
